README.md
setup.py
pyiwenli/__init__.py
pyiwenli.egg-info/PKG-INFO
pyiwenli.egg-info/SOURCES.txt
pyiwenli.egg-info/dependency_links.txt
pyiwenli.egg-info/requires.txt
pyiwenli.egg-info/top_level.txt
pyiwenli/core/__init__.py
pyiwenli/core/const.py
pyiwenli/core/lazyProperty.py
pyiwenli/core/singletonMetaClass.py
pyiwenli/handlers/__init__.py
pyiwenli/handlers/configHandler.py
pyiwenli/handlers/logHandler.py
pyiwenli/handlers/sendEmailHandler.py
pyiwenli/utils/__init__.py
pyiwenli/utils/decoractors.py
pyiwenli/utils/extract.py
pyiwenli/utils/verify.py
tests/__init__.py
tests/test_config.py
tests/test_decoractor.py
tests/test_log.py
tests/test_re.py