Metadata-Version: 1.0
Name: pyiwenli
Version: 0.0.7
Summary: 自用工具封装
Home-page: https://github.com/iwenli/pyiwenli
Author: iwenli
Author-email: admin@iwenli.org
License: MIT Licence
Keywords: pip,iwenli
Platform: any
